{
  "latestErrorEvent": {
    "code": "TYPE-001",
    "message": "Failed to generate type declaration. Execute the below cmd to reproduce and fix the error. #TYPE-001\nargs: {\"cmd\":\"npx tsc --project /home/satyajit/Documents/GitHub/MFECP/apps/cart-app/node_modules/.federation/tsconfig.a5c7b9a2d4312b02ad28c7aff551a59b.json\"}\nView the docs to see how to solve: https://module-federation.io/guide/troubleshooting/type#type-001",
    "args": {
      "cmd": "npx tsc --project /home/satyajit/Documents/GitHub/MFECP/apps/cart-app/node_modules/.federation/tsconfig.a5c7b9a2d4312b02ad28c7aff551a59b.json"
    },
    "timestamp": 1779258979055
  }
}